pgrwpy/__init__.py
pgrwpy/client.py
pgrwpy/errors.py
pgrwpy/constants/__init__.py
pgrwpy/constants/api_list.py
pgrwpy/constants/error_code.py
pgrwpy/constants/http_status_code.py
pgrwpy/constants/url.py
pgrwpy/resources/__init__.py
pgrwpy/resources/base.py
pgrwpy/resources/card.py
pgrwpy/resources/payment.py
pgrwpy/resources/reward.py
pgrwpy-0.1.4.dist-info/AUTHORS
pgrwpy-0.1.4.dist-info/LICENSE
pgrwpy-0.1.4.dist-info/METADATA
pgrwpy-0.1.4.dist-info/WHEEL
pgrwpy-0.1.4.dist-info/top_level.txt
pgrwpy-0.1.4.dist-info/RECORD
