Metadata-Version: 2.1
Name: pgrwpy
Version: 0.1.4
Summary: PG Rewards python SDK
Author: Stanley Castin
Author-email: stanleycastin19@gmail.com
License: MIT
Project-URL: Documentation, https://github.com/PGecom/python-pg-sdk/blob/main/README.md
Project-URL: Source, https://github.com/PGecom/python-pg-sdk
Keywords: PGREWARDS payment moncash CC
Classifier: Intended Audience :: Developers
Classifier: License :: OSI Approved :: Apache Software License
Classifier: Programming Language :: Python :: 3.7
Classifier: Programming Language :: Python :: 3.8
Classifier: Programming Language :: Python :: 3.9
Classifier: Programming Language :: Python :: 3.10
Classifier: Topic :: Software Development :: Libraries :: Python Modules
License-File: LICENSE
License-File: AUTHORS
Requires-Dist: requests
Provides-Extra: test
Requires-Dist: responses ; extra == 'test'
